README
setup.py
plugins/__init__.py
plugins/admin.py
plugins/api.py
plugins/forms.py
plugins/middleware.py
plugins/models.py
plugins/search_indexes.py
plugins/tests.py
plugins/urls.py
plugins/validator.py
plugins/views.py
plugins/migrations/0001_initial.py
plugins/migrations/0002_auto__add_field_plugin_repository__add_field_plugin_tracker__add_field.py
plugins/migrations/0003_auto__chg_field_pluginversion_changelog.py
plugins/migrations/0004_auto__add_field_plugin_author.py
plugins/migrations/0005_auto__add_field_plugin_email.py
plugins/migrations/0006_auto__chg_field_plugin_author__chg_field_plugin_email.py
plugins/migrations/0007_auto__add_field_plugin_rating_votes__add_field_plugin_rating_score.py
plugins/migrations/0008_auto__add_field_pluginversion_max_qg_version.py
plugins/migrations/0009_auto.py
plugins/migrations/__init__.py
plugins/templatetags/__init__.py
plugins/templatetags/plugin_utils.py
plugins/templatetags/plugins_tagcloud.py
plugins/templatetags/range_filter.py
plugins/templatetags/smart_paginate.py
qgis_plugins.egg-info/PKG-INFO
qgis_plugins.egg-info/SOURCES.txt
qgis_plugins.egg-info/dependency_links.txt
qgis_plugins.egg-info/requires.txt
qgis_plugins.egg-info/top_level.txt