Metadata-Version: 1.1
Name: qgis-plugins
Version: 0.0.1
Summary: A django pluggable used to serve a qgis plugin repository
Home-page: http://plugins.qgis.org
Author: Alessandro Pasotti
Author-email: apasotti@gmail.com
License: GPL
Keywords: qgis gis plugins osgeo
Platform: UNKNOWN
Classifier: Development Status :: 5 - Production/Stable
Classifier: Topic :: Utilities
Classifier: License :: OSI Approved :: GNU General Public License (GPL)
